tests/__init__.py
tests/test_vibdata.py
vibdata/__init__.py
vibdata/definitions.py
vibdata/deep/DeepDataset.py
vibdata/deep/__init__.py
vibdata/deep/signal/__init__.py
vibdata/deep/signal/core.py
vibdata/deep/signal/transforms.py
vibdata/raw/__init__.py
vibdata/raw/base.py
vibdata/raw/utils.py
vibdata/raw/CWRU/CWRU.csv
vibdata/raw/CWRU/CWRU.py
vibdata/raw/CWRU/__init__.py
vibdata/raw/HUST/HUST.csv
vibdata/raw/HUST/HUST.py
vibdata/raw/HUST/__init__.py
vibdata/raw/IMS/IMS.csv
vibdata/raw/IMS/IMS.py
vibdata/raw/IMS/__init__.py
vibdata/raw/MFPT/MFPT.csv
vibdata/raw/MFPT/MFPT.py
vibdata/raw/MFPT/__init__.py
vibdata/raw/PU/PU.csv
vibdata/raw/PU/PU.py
vibdata/raw/PU/__init__.py
vibdata/raw/UOC/UOC.csv
vibdata/raw/UOC/UOC.py
vibdata/raw/UOC/__init__.py
vibdata/raw/UORED/UORED.csv
vibdata/raw/UORED/UORED.py
vibdata/raw/UORED/__init__.py
vibdata/resources/labels.csv
vibdata-1.1.3.dist-info/LICENSE
vibdata-1.1.3.dist-info/METADATA
vibdata-1.1.3.dist-info/WHEEL
vibdata-1.1.3.dist-info/top_level.txt
vibdata-1.1.3.dist-info/RECORD
