Metadata-Version: 2.1
Name: vibdata
Version: 1.1.3
Summary: A package for vibration signal datasets
Home-page: https://github.com/ivarejao/vibdata/tree/signal_baseline
Author: Vitor Boenlla
License: UNKNOWN
Platform: UNKNOWN
License-File: LICENSE
Requires-Dist: essentia
Requires-Dist: gdown
Requires-Dist: numpy
Requires-Dist: opencv-python
Requires-Dist: pandas
Requires-Dist: rarfile
Requires-Dist: requests
Requires-Dist: scikit-learn
Requires-Dist: scipy
Requires-Dist: torch
Requires-Dist: tqdm
